{   
    "KPackageStructure": "Plasma/Applet",
    "KPlugin": {
        "Authors": [
            {
                "Email": "verminglue81@gmail.com",
                "Name": "VerminGlue"
            }
        ],
        "Category": "Utilities",
        "Description": "A basic timer of time spent in each activity.",
        "FormFactors": [
            "tablet",
            "handset",
            "desktop"
        ],
        "Icon": "chronometer",
        "Id": "com.example.activitytimer",
        "License": "GNU General Public License v2.0 or later",
        "Name": "My Activity Timer",
        "Version": "0.2",
        "Website": "https://github.com/VerminGlue/KDE-Activity-Tracker"
    },
    "X-Plasma-API-Minimum-Version": "6.0",
    "X-Plasma-Provides": [
        "org.kde.plasma.time",
        "org.kde.plasma.date"
    ]
}

